sizescan.py
sizescan-0.1.2.dist-info/METADATA
sizescan-0.1.2.dist-info/WHEEL
sizescan-0.1.2.dist-info/entry_points.txt
sizescan-0.1.2.dist-info/top_level.txt
sizescan-0.1.2.dist-info/RECORD
