Metadata-Version: 2.1
Name: sizescan
Version: 0.1.2
Summary: SizeScan is a script that displays the sizes of subfolders or files within a specified folder. It highlights items in red if they exceed a specified size limit.
Author: hasan
Author-email: hasanfq818@gmail.com
License: MIT
Classifier: Programming Language :: Python :: 3
Classifier: License :: OSI Approved :: MIT License
Classifier: Operating System :: OS Independent
Requires-Python: >=3.6
Requires-Dist: tqdm ==4.63.0
Requires-Dist: argparse ==1.4.0
